yt2audio/__init__.py
yt2audio/__main__.py
yt2audio-0.5.dist-info/METADATA
yt2audio-0.5.dist-info/WHEEL
yt2audio-0.5.dist-info/entry_points.txt
yt2audio-0.5.dist-info/top_level.txt
yt2audio-0.5.dist-info/RECORD
