Metadata-Version: 2.1
Name: yt2audio
Version: 0.5
Summary: YouTube Audio Downloader
Home-page: https://github.com/isuruwa/YT2AUDIO
Download-URL: https://github.com/isuruwa/YT2AUDIO/blob/main/dist/yt2audio-1.0.tar.gz
Author: MRX
Author-email: trymrx@pm.me
Classifier: Programming Language :: Python :: 3
Classifier: License :: OSI Approved :: MIT License
Classifier: Operating System :: OS Independent
Requires-Dist: ffmpeg
Requires-Dist: yt-dlp
